bm_calculator-0.1.0.dist-info/licenses/LICENSE
calculator/__init__.py
calculator/calculator.py
bm_calculator-0.1.0.dist-info/METADATA
bm_calculator-0.1.0.dist-info/WHEEL
bm_calculator-0.1.0.dist-info/top_level.txt
bm_calculator-0.1.0.dist-info/RECORD
