Metadata-Version: 2.4
Name: bm_calculator
Version: 0.1.0
Summary: My first PyPI library
Author-email: Mayur Bhowad <your@email.com>
License: MIT
Requires-Python: >=3.8
License-File: LICENSE
Dynamic: license-file
